detector/__init__.py
detector/entrypoint/__init__.py
detector/entrypoint/calibration_visualizer.py
detector/entrypoint/image_score_pipeline.py
detector/geometry/__init__.py
detector/geometry/board.py
detector/model/__init__.py
detector/model/configuration.py
detector/model/detection_models.py
detector/model/detection_result_code.py
detector/model/exception.py
detector/model/geometry_models.py
detector/model/image_models.py
detector/model/yolo_dart_class_mapping.py
detector/script/__init__.py
detector/script/image_scorer_demo.py
detector/script/visualizer_demo.py
detector/script/yolo_script.py
detector/service/__init__.py
detector/service/dart_image_scoring_service.py
detector/service/image_preprocessor.py
detector/service/calibration/__init__.py
detector/service/calibration/board_calibration_service.py
detector/service/calibration/calibration_matrix_calculator.py
detector/service/calibration/coordinate_transformer.py
detector/service/parser/__init__.py
detector/service/parser/abstract_parser.py
detector/service/parser/yolo_result_parser.py
detector/service/parser/calibration/__init__.py
detector/service/parser/calibration/calibration_point_parser_service.py
detector/service/parser/calibration/strategy/__init__.py
detector/service/parser/calibration/strategy/calibration_detection_strategy.py
detector/service/parser/calibration/strategy/calibration_point_strategy_factory.py
detector/service/parser/calibration/strategy/strategy_implementation.py
detector/service/parser/dart/__init__.py
detector/service/parser/dart/dart_parser_service.py
detector/service/scoring/__init__.py
detector/service/scoring/dart_point_score_calculator.py
detector/service/scoring/dart_scoring_service.py
detector/util/__init__.py
detector/util/file_utils.py
detector/util/math_utils.py
detector/yolo/__init__.py
detector/yolo/dart_detector.py
detector/yolo/dart_scorer.pt
detector/yolo/dartboard_cropper.py
detector/yolo/dartboard_detection.pt
dart_detection-0.1.5.dist-info/METADATA
dart_detection-0.1.5.dist-info/WHEEL
dart_detection-0.1.5.dist-info/entry_points.txt
dart_detection-0.1.5.dist-info/licenses/LICENSE
dart_detection-0.1.5.dist-info/RECORD
