Metadata-Version: 2.4
Name: dart-detection
Version: 0.1.5
Summary: A Python package for automatic dart detection and scoring using computer vision 
Project-URL: Repository, https://github.com/dmall00/dart-detection
Project-URL: Issues, https://github.com/dmall00/dart-detection/issues
Project-URL: Documentation, https://github.com/dmall00/dart-detection#readme
Author-email: David Mall <mall.david@web.de>
License:                     GNU GENERAL PUBLIC LICENSE
License-File: LICENSE
Keywords: computer-vision,dart,detection,scoring,yolo
Classifier: Development Status :: 3 - Alpha
Classifier: Intended Audience :: Developers
Classifier: License :: OSI Approved :: GNU General Public License v3 or later (GPLv3+)
Classifier: Programming Language :: Python :: 3
Classifier: Programming Language :: Python :: 3.11
Classifier: Programming Language :: Python :: 3.12
Classifier: Topic :: Scientific/Engineering :: Image Recognition
Requires-Python: <3.13,>=3.11
Requires-Dist: numpy>=2.2.6
Requires-Dist: opencv-python>=4.11.0.86
Requires-Dist: pydantic>=2.11.5
Requires-Dist: ultralytics>=8.3.147
